coapsttkl/__init__.py
coapsttkl/blockwise.py
coapsttkl/credentials.py
coapsttkl/defaults.py
coapsttkl/error.py
coapsttkl/interfaces.py
coapsttkl/message.py
coapsttkl/messagemanager.py
coapsttkl/meta.py
coapsttkl/options.py
coapsttkl/optiontypes.py
coapsttkl/oscore.py
coapsttkl/oscore_sitewrapper.py
coapsttkl/pipe.py
coapsttkl/protocol.py
coapsttkl/resource.py
coapsttkl/tokenmanager.py
coapsttkl/cli/__init__.py
coapsttkl/cli/client.py
coapsttkl/cli/common.py
coapsttkl/cli/defaults.py
coapsttkl/cli/fileserver.py
coapsttkl/cli/proxy.py
coapsttkl/cli/rd.py
coapsttkl/numbers/__init__.py
coapsttkl/numbers/codes.py
coapsttkl/numbers/constants.py
coapsttkl/numbers/contentformat.py
coapsttkl/numbers/optionnumbers.py
coapsttkl/numbers/types.py
coapsttkl/proxy/__init__.py
coapsttkl/proxy/client.py
coapsttkl/proxy/server.py
coapsttkl/resourcedirectory/__init__.py
coapsttkl/resourcedirectory/client/__init__.py
coapsttkl/resourcedirectory/client/register.py
coapsttkl/transports/__init__.py
coapsttkl/transports/generic_udp.py
coapsttkl/transports/oscore.py
coapsttkl/transports/rfc8323common.py
coapsttkl/transports/simple6.py
coapsttkl/transports/simplesocketserver.py
coapsttkl/transports/tcp.py
coapsttkl/transports/tinydtls.py
coapsttkl/transports/tinydtls_server.py
coapsttkl/transports/tls.py
coapsttkl/transports/udp6.py
coapsttkl/transports/ws.py
coapsttkl/util/__init__.py
coapsttkl/util/cli.py
coapsttkl/util/contenttype.py
coapsttkl/util/cryptography_additions.py
coapsttkl/util/linkformat.py
coapsttkl/util/linkformat_pygments.py
coapsttkl/util/prettyprint.py
coapsttkl/util/pyodide_websockets.py
coapsttkl/util/socknumbers.py
coapsttkl/util/uri.py
coapsttkl/util/asyncio/__init__.py
coapsttkl/util/asyncio/getaddrinfo_addrconfig.py
coapsttkl/util/asyncio/recvmsg.py
coapsttkl/util/asyncio/timeoutdict.py
coapsttkl/util/vendored/link_header.py
coapsttkl-0.0.24.dist-info/LICENSE
coapsttkl-0.0.24.dist-info/METADATA
coapsttkl-0.0.24.dist-info/WHEEL
coapsttkl-0.0.24.dist-info/top_level.txt
coapsttkl-0.0.24.dist-info/RECORD
